api_gateway_v2_to_wsgi.py
api_gateway_v2_to_wsgi-1.1.1.dist-info/LICENSE
api_gateway_v2_to_wsgi-1.1.1.dist-info/METADATA
api_gateway_v2_to_wsgi-1.1.1.dist-info/WHEEL
api_gateway_v2_to_wsgi-1.1.1.dist-info/top_level.txt
api_gateway_v2_to_wsgi-1.1.1.dist-info/RECORD
