Metadata-Version: 2.1
Name: api-gateway-v2-to-wsgi
Version: 1.1.1
Summary: translation from the aws api gateway v2.0 lambda event to wsgi
Home-page: https://github.com/asottile/api-gateway-v2-to-wsgi
Author: Anthony Sottile
Author-email: asottile@umich.edu
License: MIT
Classifier: License :: OSI Approved :: MIT License
Classifier: Programming Language :: Python :: 3
Classifier: Programming Language :: Python :: 3 :: Only
Classifier: Programming Language :: Python :: Implementation :: CPython
Requires-Python: >=3.8
License-File: LICENSE
